README.md
setup.py
linelime/__init__.py
linelime.egg-info/PKG-INFO
linelime.egg-info/SOURCES.txt
linelime.egg-info/dependency_links.txt
linelime.egg-info/requires.txt
linelime.egg-info/top_level.txt