Metadata-Version: 1.1
Name: linelime
Version: 0.2.2.Beta
Summary: Get Line Timeline Data
Home-page: https://github.com/cacadosman/linelime
Author: Fadli Maulana M
Author-email: wetmanz23@gmail.com
License: MIT
Platform: UNKNOWN
Classifier: License :: OSI Approved :: MIT License
Classifier: Programming Language :: Python :: 3
Classifier: Programming Language :: Python :: 3.7
